{
  "variants":{
    "facing=north,occupied=false,part=head": { "model": "kwemsmod:limeoakbedhead", "y": 180 },
    "facing=south,occupied=false,part=head": { "model": "kwemsmod:limeoakbedhead"},
    "facing=west,occupied=false,part=head": { "model": "kwemsmod:limeoakbedhead", "y": 90 },
    "facing=east,occupied=false,part=head": { "model": "kwemsmod:limeoakbedhead", "y": -90},
    "facing=north,occupied=true,part=head": { "model": "kwemsmod:limeoakbedhead", "y": 180 },
    "facing=south,occupied=true,part=head": { "model": "kwemsmod:limeoakbedhead"},
    "facing=west,occupied=true,part=head": { "model": "kwemsmod:limeoakbedhead", "y": 90 },
    "facing=east,occupied=true,part=head": { "model": "kwemsmod:limeoakbedhead", "y": -90},
    "facing=north,occupied=false,part=foot": { "model": "kwemsmod:limeoakbedbase", "y": 180 },
    "facing=south,occupied=false,part=foot": { "model": "kwemsmod:limeoakbedbase"},
    "facing=west,occupied=false,part=foot": { "model": "kwemsmod:limeoakbedbase", "y": 90 },
    "facing=east,occupied=false,part=foot": { "model": "kwemsmod:limeoakbedbase", "y": -90},
    "facing=north,occupied=true,part=foot": { "model": "kwemsmod:limeoakbedbase", "y": 180 },
    "facing=south,occupied=true,part=foot": { "model": "kwemsmod:limeoakbedbase"},
    "facing=west,occupied=true,part=foot": { "model": "kwemsmod:limeoakbedbase", "y": 90 },
    "facing=east,occupied=true,part=foot": { "model": "kwemsmod:limeoakbedbase", "y": -90}
  }
}
